reddit2text/__init__.py
reddit2text/main.py
reddit2text-0.0.9.dist-info/LICENSE
reddit2text-0.0.9.dist-info/METADATA
reddit2text-0.0.9.dist-info/WHEEL
reddit2text-0.0.9.dist-info/top_level.txt
reddit2text-0.0.9.dist-info/RECORD
