Metadata-Version: 2.1
Name: reddit2text
Version: 0.0.9
Summary: Convert Reddit posts to text
Author: Nicholas Hansen-Feruch
Author-email: nicholas.feruch@gmail.com
Keywords: python,reddit,text conversion,reddit api,praw,reddit to text,reddit comments,social media analysis
Classifier: Development Status :: 3 - Alpha
Classifier: Intended Audience :: Developers
Classifier: Topic :: Software Development :: Libraries :: Python Modules
Classifier: Programming Language :: Python :: 3
Classifier: License :: OSI Approved :: MIT License
Classifier: Operating System :: OS Independent
Requires-Python: >=3.6
License-File: LICENSE
Requires-Dist: praw
